kmprograms_calc/__init__.py
kmprograms_calc/action/__init__.py
kmprograms_calc/action/mul_action.py
kmprograms_calc/action/sub_action.py
kmprograms_calc/operations.py
kmprograms_calc-0.2.0.dist-info/METADATA
kmprograms_calc-0.2.0.dist-info/WHEEL
kmprograms_calc-0.2.0.dist-info/RECORD
